bs4tag/__init__.py
bs4tag/doc.py
bs4tag/indentation.py
bs4tag/py.typed
bs4tag/simpledoc.py
bs4tag-0.1.0.dist-info/LICENSE
bs4tag-0.1.0.dist-info/METADATA
bs4tag-0.1.0.dist-info/WHEEL
bs4tag-0.1.0.dist-info/top_level.txt
bs4tag-0.1.0.dist-info/RECORD
