Metadata-Version: 2.1
Name: bs4tag
Version: 0.1.0
Summary: Generate HTML or XML in a pythonic way. Pure python alternative to web template engines. Based on BeautifulSoup parser. Can fill HTML forms with default values and error messages.
Home-page: https://www.yattag.org
Author: ceprio
Author-email: c.pypi@zone-c4.com
License: UNKNOWN
Keywords: html,template,templating,xml,document,form,rendering,beautifulsoup
Platform: UNKNOWN
Classifier: Development Status :: 4 - Beta
Classifier: Environment :: Web Environment
Classifier: Intended Audience :: Developers
Classifier: License :: OSI Approved :: GNU Library or Lesser General Public License (LGPL)
Classifier: Operating System :: OS Independent
Classifier: Programming Language :: Python
Classifier: Programming Language :: Python :: 3
Classifier: Programming Language :: Python :: 3.2
Classifier: Programming Language :: Python :: 3.3
Classifier: Programming Language :: Python :: 3.4
Classifier: Programming Language :: Python :: 3.5
Classifier: Programming Language :: Python :: 3.6
Classifier: Programming Language :: Python :: 3.7
Classifier: Programming Language :: Python :: 3.8
Classifier: Programming Language :: Python :: 3.9
Classifier: Programming Language :: Python :: 3.10
Classifier: Topic :: Internet :: WWW/HTTP
Classifier: Topic :: Internet :: WWW/HTTP :: Dynamic Content
Classifier: Topic :: Software Development :: Libraries :: Python Modules
Requires-Python: >=3.2.0
License-File: LICENSE
Requires-Dist: bs4
Requires-Dist: typing ; python_version < "3.5"
